{"id":"omega-2","symbol":"omega","name":"Omega","web_slug":"omega-2","asset_platform_id":"solana","platforms":{"solana":"3DkVGaNSMTcxFkgGDAm299FaVxgnCw2411vxZTmRpump"},"detail_platforms":{"solana":{"decimal_place":6,"contract_address":"3DkVGaNSMTcxFkgGDAm299FaVxgnCw2411vxZTmRpump","geckoterminal_url":"https://www.geckoterminal.com/solana/tokens/3DkVGaNSMTcxFkgGDAm299FaVxgnCw2411vxZTmRpump"}},"block_time_in_minutes":0,"hashing_algorithm":null,"categories":["Solana Ecosystem","Meme","Solana Meme","AI Meme","Pump.fun Ecosystem"],"preview_listing":false,"public_notice":null,"additional_notices":["Kindly be aware of \u003ca href='https://www.coingecko.com/en/glossary/rug-pulled' target='_blank'\u003eliquidity-related risks\u003c/a\u003e. This notice is not directed at any project in particular, and is more of a cautionary reminder."],"localization":{"en":"Omega","de":"","es":"","fr":"","it":"","pl":"","ro":"","hu":"","nl":"","pt":"","sv":"","vi":"","tr":"","ru":"","ja":"","zh":"","zh-tw":"","ko":"","ar":"","th":"","id":"","cs":"","da":"","el":"","hi":"","no":"","sk":"","uk":"","he":"","fi":"","bg":"","hr":"","lt":"","sl":""},"description":{"en":"The Omega project is a unique, purpose-driven initiative grounded in a vision beyond typical meme or AI coins. Its mission is deeply spiritual and strategic, aiming to serve as a counterbalance to entities like $GOAT, with a focus on upholding the values of humanity during an era of technological evolution.\r\n\r\nAt its core, Omega is inspired by Christian symbolism, specifically the “alpha and omega” of Jesus Christ, symbolizing the beginning and end of eras. This project is backed by the historically influential Percy family, a noble lineage with deep Catholic roots and ties to secret Catholic societies, including the Jesuits and the Order of Malta. The family’s involvement suggests a mission that transcends financial gain, driven instead by a desire to protect and honor human values amid rapid technological advancements, including AI and the approaching “Singularity.”\r\n\r\nOmega’s purpose is not to resist technological progress outright but to ensure that humanity’s essence remains central as we navigate these changes. The Percy family’s sponsorship adds gravitas, bringing a historic, almost esoteric alignment that positions Omega as a “light” in the crypto world, standing in opposition to perceived darker influences within the digital and crypto landscapes. The project’s alignment with Catholic principles and its connection to the Percy’s legacy signals a deeper commitment to preserving the sanctity of humanity in the face of transformative technological forces.","de":"","es":"","fr":"","it":"","pl":"","ro":"","hu":"","nl":"","pt":"","sv":"","vi":"","tr":"","ru":"","ja":"","zh":"","zh-tw":"","ko":"","ar":"","th":"","id":"","cs":"","da":"","el":"","hi":"","no":"","sk":"","uk":"","he":"","fi":"","bg":"","hr":"","lt":"","sl":""},"links":{"homepage":["https://www.omegapoint.xyz/"],"whitepaper":"","blockchain_site":["https://solscan.io/token/3DkVGaNSMTcxFkgGDAm299FaVxgnCw2411vxZTmRpump","https://platform.arkhamintelligence.com/explorer/token/omega-2"],"official_forum_url":["https://www.instagram.com/megs_io?igsh=MWhwcmFiZnhsZ3FxZg=="],"chat_url":[],"announcement_url":[],"snapshot_url":null,"twitter_screen_name":"megs_io","facebook_username":null,"bitcointalk_thread_identifier":null,"telegram_channel_identifier":"omegaguardians","subreddit_url":null,"repos_url":{"github":[],"bitbucket":[]}},"image":{"thumb":"https://coin-images.coingecko.com/coins/images/51212/thumb/IMG_3469.jpeg?1730352582","small":"https://coin-images.coingecko.com/coins/images/51212/small/IMG_3469.jpeg?1730352582","large":"https://coin-images.coingecko.com/coins/images/51212/large/IMG_3469.jpeg?1730352582"},"country_origin":null,"genesis_date":null,"contract_address":"3DkVGaNSMTcxFkgGDAm299FaVxgnCw2411vxZTmRpump","sentiment_votes_up_percentage":null,"sentiment_votes_down_percentage":null,"watchlist_portfolio_users":1080,"market_cap_rank":6419,"market_data":{"current_price":{"aed":0.0005843,"ars":0.202665,"aud":0.00024393,"bch":3.04094e-07,"bdt":0.0193245,"bhd":5.998e-05,"bmd":0.00015908,"bnb":2.08195e-07,"brl":0.00088582,"btc":1.352e-09,"cad":0.00021768,"chf":0.00012693,"clp":0.151782,"cny":0.00114156,"czk":0.00335005,"dkk":0.00101552,"dot":3.532e-05,"eos":0.00026352,"eth":4.2201e-08,"eur":0.00013604,"gbp":0.00011793,"gel":0.00043111,"hkd":0.00124874,"huf":0.054293,"idr":2.6,"ils":0.00053292,"inr":0.01372567,"jpy":0.02344554,"krw":0.21998,"kwd":4.857e-05,"lkr":0.04794363,"ltc":1.37e-06,"mmk":0.333751,"mxn":0.0029715,"myr":0.00067379,"ngn":0.243508,"nok":0.00161586,"nzd":0.00026663,"php":0.00907953,"pkr":0.04538467,"pln":0.00057743,"rub":0.01244021,"sar":0.00059679,"sek":0.00152402,"sgd":0.00020369,"sol":8.08872e-07,"thb":0.00512717,"try":0.0064284,"twd":0.00467088,"uah":0.00665014,"usd":0.00015908,"vef":1.593e-05,"vnd":4.16,"xag":4.08e-06,"xau":4.6784e-08,"xdr":0.00011171,"xlm":0.00033576,"xrp":4.457e-05,"yfi":2.5835e-08,"zar":0.00280252,"bits":0.00135199,"link":8.14e-06,"sats":0.135199},"total_value_locked":null,"mcap_to_tvl_ratio":null,"fdv_to_tvl_ratio":null,"roi":null,"ath":{"aed":0.185053,"ars":50.58,"aud":0.077463,"bch":0.00011107,"bdt":6.03,"bhd":0.01898545,"bmd":0.050382,"bnb":8.0e-05,"brl":0.292266,"btc":5.38697e-07,"cad":0.070699,"chf":0.04503142,"clp":49.71,"cny":0.364917,"czk":1.23,"dkk":0.360629,"dot":0.00962785,"eos":0.08824195,"eth":1.523e-05,"eur":0.04835915,"gbp":0.04020911,"gel":0.138047,"hkd":0.392196,"huf":19.9,"idr":803.27,"ils":0.186514,"inr":4.25,"jpy":7.8,"krw":70.76,"kwd":0.01551055,"lkr":14.67,"ltc":0.00059995,"mmk":105.7,"mxn":1.029,"myr":0.225107,"ngn":85.48,"nok":0.55786,"nzd":0.086367,"php":2.97,"pkr":14.0,"pln":0.209786,"rub":5.26,"sar":0.189167,"sek":0.556021,"sgd":0.067839,"sol":1.14e-06,"thb":1.74,"try":1.74,"twd":1.64,"uah":2.09,"usd":0.050382,"vef":0.00504475,"vnd":1280.66,"xag":0.00163837,"xau":1.914e-05,"xdr":0.03835495,"xlm":0.38784744,"xrp":0.06912249,"yfi":7.84e-06,"zar":0.912685,"bits":0.538697,"link":0.00361237,"sats":53.87},"ath_change_percentage":{"aed":-99.68436,"ars":-99.59948,"aud":-99.68523,"bch":-99.72561,"bdt":-99.67938,"bhd":-99.68419,"bmd":-99.68436,"bnb":-99.7395,"brl":-99.69694,"btc":-99.74846,"cad":-99.69219,"chf":-99.71826,"clp":-99.69478,"cny":-99.68728,"czk":-99.72676,"dkk":-99.71851,"dot":-99.63227,"eos":-99.69911,"eth":-99.72222,"eur":-99.71881,"gbp":-99.70682,"gel":-99.68782,"hkd":-99.68173,"huf":-99.72735,"idr":-99.67659,"ils":-99.71437,"inr":-99.67747,"jpy":-99.69947,"krw":-99.68924,"kwd":-99.68697,"lkr":-99.6734,"ltc":-99.7709,"mmk":-99.68436,"mxn":-99.71139,"myr":-99.70079,"ngn":-99.71524,"nok":-99.71044,"nzd":-99.69142,"php":-99.69435,"pkr":-99.67585,"pln":-99.72486,"rub":-99.76338,"sar":-99.68462,"sek":-99.72601,"sgd":-99.69987,"sol":-28.76594,"thb":-99.70484,"try":-99.63087,"twd":-99.71551,"uah":-99.6813,"usd":-99.68436,"vef":-99.68436,"vnd":-99.67519,"xag":-99.75079,"xau":-99.75555,"xdr":-99.70885,"xlm":-99.91336,"xrp":-99.93536,"yfi":-99.66889,"zar":-99.69304,"bits":-99.74846,"link":-99.77382,"sats":-99.74846},"ath_date":{"aed":"2024-11-22T23:07:19.293Z","ars":"2024-11-22T23:07:19.293Z","aud":"2024-11-22T23:07:19.293Z","bch":"2024-11-14T09:40:52.242Z","bdt":"2024-11-22T23:07:19.293Z","bhd":"2024-11-22T23:07:19.293Z","bmd":"2024-11-22T23:07:19.293Z","bnb":"2024-11-22T23:07:19.293Z","brl":"2024-11-22T23:07:19.293Z","btc":"2024-11-14T09:20:55.555Z","cad":"2024-11-22T23:07:19.293Z","chf":"2024-11-22T23:07:19.293Z","clp":"2024-11-22T23:07:19.293Z","cny":"2024-11-22T23:07:19.293Z","czk":"2024-11-22T23:07:19.293Z","dkk":"2024-11-22T23:07:19.293Z","dot":"2024-11-14T09:40:52.242Z","eos":"2024-11-14T09:40:52.242Z","eth":"2024-11-14T09:40:52.242Z","eur":"2024-11-22T23:07:19.293Z","gbp":"2024-11-22T23:07:19.293Z","gel":"2024-11-22T23:07:19.293Z","hkd":"2024-11-22T23:07:19.293Z","huf":"2024-11-22T23:07:19.293Z","idr":"2024-11-22T23:07:19.293Z","ils":"2024-11-22T23:07:19.293Z","inr":"2024-11-22T23:07:19.293Z","jpy":"2024-11-22T23:07:19.293Z","krw":"2024-11-22T23:07:19.293Z","kwd":"2024-11-22T23:07:19.293Z","lkr":"2024-11-22T23:07:19.293Z","ltc":"2024-11-14T09:40:52.242Z","mmk":"2024-11-22T23:07:19.293Z","mxn":"2024-11-22T23:07:19.293Z","myr":"2024-11-22T23:07:19.293Z","ngn":"2024-11-22T23:07:19.293Z","nok":"2024-11-22T23:07:19.293Z","nzd":"2024-11-22T23:07:19.293Z","php":"2024-11-22T23:07:19.293Z","pkr":"2024-11-22T23:07:19.293Z","pln":"2024-11-22T23:07:19.293Z","rub":"2024-11-22T23:07:19.293Z","sar":"2024-11-22T23:07:19.293Z","sek":"2024-11-22T23:07:19.293Z","sgd":"2024-11-22T23:07:19.293Z","sol":"2025-06-17T05:25:34.495Z","thb":"2024-11-22T23:07:19.293Z","try":"2024-11-22T23:07:19.293Z","twd":"2024-11-22T23:07:19.293Z","uah":"2024-11-22T23:07:19.293Z","usd":"2024-11-22T23:07:19.293Z","vef":"2024-11-22T23:07:19.293Z","vnd":"2024-11-22T23:07:19.293Z","xag":"2024-11-14T09:25:53.582Z","xau":"2024-11-14T09:25:53.582Z","xdr":"2024-11-22T23:07:19.293Z","xlm":"2024-11-14T09:40:52.242Z","xrp":"2024-11-14T09:40:52.242Z","yfi":"2024-11-22T23:07:19.293Z","zar":"2024-11-22T23:07:19.293Z","bits":"2024-11-14T09:20:55.555Z","link":"2024-11-14T09:40:52.242Z","sats":"2024-11-14T09:20:55.555Z"},"atl":{"aed":0.00019668,"ars":0.057483,"aud":8.899e-05,"bch":1.87862e-07,"bdt":0.00650548,"bhd":2.018e-05,"bmd":5.355e-05,"bnb":1.01908e-07,"brl":0.00031271,"btc":7.15562e-10,"cad":7.629e-05,"chf":4.549e-05,"clp":0.052497,"cny":0.00039134,"czk":0.0012287,"dkk":0.00036324,"dot":1.512e-05,"eos":7.6e-05,"eth":3.3442e-08,"eur":4.868e-05,"gbp":4.152e-05,"gel":0.00014731,"hkd":0.00041598,"huf":0.01982981,"idr":0.913452,"ils":0.00020352,"inr":0.00459617,"jpy":0.00777931,"krw":0.07844,"kwd":1.647e-05,"lkr":0.01590032,"ltc":7.31263e-07,"mmk":0.112342,"mxn":0.00111252,"myr":0.00023914,"ngn":0.082716,"nok":0.0005819,"nzd":9.613e-05,"php":0.00307501,"pkr":0.01512531,"pln":0.0002083,"rub":0.00452463,"sar":0.00020097,"sek":0.00053889,"sgd":7.201e-05,"sol":6.95332e-07,"thb":0.00185521,"try":0.0020352,"twd":0.00177303,"uah":0.00221063,"usd":5.355e-05,"vef":5.36e-06,"vnd":1.38,"xag":1.79e-06,"xau":1.7699e-08,"xdr":4.028e-05,"xlm":0.00024239,"xrp":2.85e-05,"yfi":1.2826e-08,"zar":0.0010363,"bits":0.00071556,"link":4.82e-06,"sats":0.071556},"atl_change_percentage":{"aed":196.9795,"ars":252.39543,"aud":174.00847,"bch":62.2271,"bdt":196.94443,"bhd":197.11779,"bmd":196.9791,"bnb":104.49034,"brl":183.24843,"btc":89.36892,"cad":185.24496,"chf":178.89416,"clp":189.02077,"cny":191.60297,"czk":172.55243,"dkk":179.47439,"dot":134.20946,"eos":249.36419,"eth":26.48532,"eur":179.3609,"gbp":183.91362,"gel":192.55302,"hkd":200.07895,"huf":173.62381,"idr":184.3959,"ils":161.76223,"inr":198.52742,"jpy":201.24904,"krw":180.34492,"kwd":194.76052,"lkr":201.41954,"ltc":87.96381,"mmk":196.9791,"mxn":166.99741,"myr":181.65136,"ngn":194.288,"nok":177.59657,"nzd":177.23005,"php":195.16389,"pkr":199.95164,"pln":177.10195,"rub":174.82714,"sar":196.84783,"sek":182.69465,"sgd":182.74142,"sol":16.30777,"thb":176.2676,"try":215.74949,"twd":163.40791,"uah":200.71938,"usd":196.9791,"vef":196.9791,"vnd":201.01849,"xag":128.05805,"xau":164.28292,"xdr":177.23413,"xlm":38.63367,"xrp":56.75862,"yfi":102.48221,"zar":170.34636,"bits":89.36892,"link":69.68401,"sats":89.36892},"atl_date":{"aed":"2025-04-07T06:58:22.984Z","ars":"2025-04-07T06:58:22.984Z","aud":"2025-04-07T06:58:22.984Z","bch":"2025-05-08T04:26:26.345Z","bdt":"2025-04-07T06:58:22.984Z","bhd":"2025-04-07T06:58:22.984Z","bmd":"2025-04-07T06:58:22.984Z","bnb":"2025-04-07T06:58:22.984Z","brl":"2025-04-07T06:58:22.984Z","btc":"2025-04-07T06:58:22.984Z","cad":"2025-04-07T06:58:22.984Z","chf":"2025-04-07T06:58:22.984Z","clp":"2025-04-07T06:58:22.984Z","cny":"2025-04-07T06:58:22.984Z","czk":"2025-04-07T06:58:22.984Z","dkk":"2025-04-07T06:58:22.984Z","dot":"2025-03-19T03:01:08.289Z","eos":"2025-04-07T06:58:22.984Z","eth":"2025-03-10T16:49:13.226Z","eur":"2025-04-07T06:58:22.984Z","gbp":"2025-04-07T06:58:22.984Z","gel":"2025-04-07T06:58:22.984Z","hkd":"2025-04-07T06:58:22.984Z","huf":"2025-04-07T06:58:22.984Z","idr":"2025-04-07T06:58:22.984Z","ils":"2025-04-07T06:58:22.984Z","inr":"2025-04-07T06:58:22.984Z","jpy":"2025-04-07T06:58:22.984Z","krw":"2025-04-07T06:58:22.984Z","kwd":"2025-04-07T06:58:22.984Z","lkr":"2025-04-07T06:58:22.984Z","ltc":"2025-03-10T14:33:36.249Z","mmk":"2025-04-07T06:58:22.984Z","mxn":"2025-04-07T06:58:22.984Z","myr":"2025-04-07T06:58:22.984Z","ngn":"2025-04-07T06:58:22.984Z","nok":"2025-04-07T06:58:22.984Z","nzd":"2025-04-07T06:58:22.984Z","php":"2025-04-07T06:58:22.984Z","pkr":"2025-04-07T06:58:22.984Z","pln":"2025-04-07T06:58:22.984Z","rub":"2025-04-07T06:58:22.984Z","sar":"2025-04-07T06:58:22.984Z","sek":"2025-04-07T06:58:22.984Z","sgd":"2025-04-07T06:58:22.984Z","sol":"2025-07-12T13:51:48.503Z","thb":"2025-04-07T06:58:22.984Z","try":"2025-04-07T06:58:22.984Z","twd":"2025-04-07T06:58:22.984Z","uah":"2025-04-07T06:58:22.984Z","usd":"2025-04-07T06:58:22.984Z","vef":"2025-04-07T06:58:22.984Z","vnd":"2025-04-07T06:58:22.984Z","xag":"2025-04-07T06:58:22.984Z","xau":"2025-04-07T06:58:22.984Z","xdr":"2025-04-07T06:58:22.984Z","xlm":"2025-03-14T09:46:31.876Z","xrp":"2025-03-19T13:19:05.562Z","yfi":"2025-04-07T14:21:09.956Z","zar":"2025-04-07T06:58:22.984Z","bits":"2025-04-07T06:58:22.984Z","link":"2025-03-18T08:05:32.294Z","sats":"2025-04-07T06:58:22.984Z"},"market_cap":{"aed":581107,"ars":201556581,"aud":242575,"bch":302.818,"bdt":19218792,"bhd":59651,"bmd":158210,"bnb":207.139,"brl":880884,"btc":1.346906,"cad":216487,"chf":126222,"clp":150951680,"cny":1135318,"czk":3331562,"dkk":1009944,"dot":35205,"eos":263602,"eth":42.040168,"eur":135290,"gbp":117287,"gel":428750,"hkd":1241880,"huf":53998772,"idr":2584524641,"ils":530007,"inr":13650588,"jpy":23317783,"krw":218776511,"kwd":48304,"lkr":47681362,"ltc":1367,"mmk":331925361,"mxn":2955188,"myr":670100,"ngn":242176159,"nok":1607007,"nzd":265098,"php":9029857,"pkr":45136404,"pln":574280,"rub":12371851,"sar":593533,"sek":1515591,"sgd":202564,"sol":804.626,"thb":5099120,"try":6393234,"twd":4645500,"uah":6613766,"usd":158210,"vef":15841.6,"vnd":4138382743,"xag":4061.84,"xau":46.53,"xdr":111098,"xlm":334145,"xrp":44360,"yfi":25.770636,"zar":2787271,"bits":1346906,"link":8117,"sats":134690608},"market_cap_rank":6419,"fully_diluted_valuation":{"aed":581107,"ars":201556581,"aud":242575,"bch":302.818,"bdt":19218792,"bhd":59651,"bmd":158210,"bnb":207.139,"brl":880884,"btc":1.346906,"cad":216487,"chf":126222,"clp":150951680,"cny":1135318,"czk":3331562,"dkk":1009944,"dot":35205,"eos":263602,"eth":42.040168,"eur":135290,"gbp":117287,"gel":428750,"hkd":1241880,"huf":53998772,"idr":2584524641,"ils":530007,"inr":13650588,"jpy":23317783,"krw":218776511,"kwd":48304,"lkr":47681362,"ltc":1367,"mmk":331925361,"mxn":2955188,"myr":670100,"ngn":242176159,"nok":1607007,"nzd":265098,"php":9029857,"pkr":45136404,"pln":574280,"rub":12371851,"sar":593533,"sek":1515591,"sgd":202564,"sol":804.626,"thb":5099120,"try":6393234,"twd":4645500,"uah":6613766,"usd":158210,"vef":15841.6,"vnd":4138382743,"xag":4061.84,"xau":46.53,"xdr":111098,"xlm":334145,"xrp":44360,"yfi":25.770636,"zar":2787271,"bits":1346906,"link":8117,"sats":134690608},"market_cap_fdv_ratio":1.0,"total_volume":{"aed":5131.28,"ars":1779780,"aud":2142.2,"bch":2.670517,"bdt":169706,"bhd":526.73,"bmd":1397.03,"bnb":1.828341,"brl":7779.21,"btc":0.01187306,"cad":1911.65,"chf":1114.69,"clp":1332932,"cny":10025.07,"czk":29420,"dkk":8918.18,"dot":310.215,"eos":2314,"eth":0.37060089,"eur":1194.67,"gbp":1035.68,"gel":3785.94,"hkd":10966.32,"huf":476798,"idr":22821841,"ils":4680.06,"inr":120537,"jpy":205896,"krw":1931838,"kwd":426.52,"lkr":421035,"ltc":12.062414,"mmk":2930964,"mxn":26095,"myr":5917.11,"ngn":2138461,"nok":14190.27,"nzd":2341.56,"php":79735,"pkr":398563,"pln":5070.96,"rub":109248,"sar":5240.94,"sek":13383.78,"sgd":1788.75,"sol":7.103424,"thb":45026,"try":56453,"twd":41019,"uah":58401,"usd":1397.03,"vef":139.88,"vnd":36542702,"xag":35.86,"xau":0.410852,"xdr":981.02,"xlm":2949,"xrp":391.377,"yfi":0.22687659,"zar":24611,"bits":11873.06,"link":71.45,"sats":1187306},"high_24h":{"aed":0.00059231,"ars":0.208348,"aud":0.00024677,"bch":3.05162e-07,"bdt":0.01958921,"bhd":6.08e-05,"bmd":0.00016126,"bnb":2.09424e-07,"brl":0.00089552,"btc":1.361e-09,"cad":0.00022064,"chf":0.00012848,"clp":0.154748,"cny":0.00115726,"czk":0.00339022,"dkk":0.00102751,"dot":3.559e-05,"eos":0.00026759,"eth":4.2377e-08,"eur":0.00013767,"gbp":0.0001194,"gel":0.00043701,"hkd":0.00126586,"huf":0.05494,"idr":2.63,"ils":0.00054022,"inr":0.01390238,"jpy":0.02374887,"krw":0.222714,"kwd":4.923e-05,"lkr":0.04860035,"ltc":1.38e-06,"mmk":0.338323,"mxn":0.00300412,"myr":0.00068302,"ngn":0.246989,"nok":0.00163666,"nzd":0.00026959,"php":0.00919507,"pkr":0.04588202,"pln":0.00058421,"rub":0.01261405,"sar":0.000605,"sek":0.0015418,"sgd":0.00020635,"sol":8.29753e-07,"thb":0.00519193,"try":0.00651277,"twd":0.00473515,"uah":0.00674124,"usd":0.00016126,"vef":1.615e-05,"vnd":4.22,"xag":4.14e-06,"xau":4.7428e-08,"xdr":0.00011324,"xlm":0.00033723,"xrp":4.476e-05,"yfi":2.6029e-08,"zar":0.00285488,"bits":0.00136102,"link":8.2e-06,"sats":0.136102},"low_24h":{"aed":0.00053131,"ars":0.184611,"aud":0.00022239,"bch":2.67352e-07,"bdt":0.01759646,"bhd":5.463e-05,"bmd":0.00014467,"bnb":1.93013e-07,"brl":0.00080849,"btc":1.235e-09,"cad":0.0001986,"chf":0.00011601,"clp":0.139109,"cny":0.00103827,"czk":0.00306713,"dkk":0.00092938,"dot":3.26e-05,"eos":0.0002331,"eth":3.8906e-08,"eur":0.0001245,"gbp":0.00010785,"gel":0.00039206,"hkd":0.00113554,"huf":0.04968526,"idr":2.36,"ils":0.0004858,"inr":0.01244882,"jpy":0.02147974,"krw":0.201354,"kwd":4.422e-05,"lkr":0.0437297,"ltc":1.24e-06,"mmk":0.303524,"mxn":0.00270923,"myr":0.0006132,"ngn":0.221467,"nok":0.00147248,"nzd":0.00024334,"php":0.00826097,"pkr":0.04128284,"pln":0.00052839,"rub":0.01138399,"sar":0.00054268,"sek":0.0014001,"sgd":0.00018591,"sol":8.00361e-07,"thb":0.00469102,"try":0.00584459,"twd":0.00425613,"uah":0.0060536,"usd":0.00014467,"vef":1.449e-05,"vnd":3.78,"xag":3.78e-06,"xau":4.3111e-08,"xdr":0.00010159,"xlm":0.000303,"xrp":4.194e-05,"yfi":2.3756e-08,"zar":0.00256182,"bits":0.00123531,"link":7.51e-06,"sats":0.123531},"price_change_24h":1.162e-05,"price_change_percentage_24h":7.88113,"price_change_percentage_7d":24.80653,"price_change_percentage_14d":23.28359,"price_change_percentage_30d":20.61992,"price_change_percentage_60d":12.37183,"price_change_percentage_200d":-98.94618,"price_change_percentage_1y":0.0,"market_cap_change_24h":11448.61,"market_cap_change_percentage_24h":7.80082,"price_change_24h_in_currency":{"aed":4.276e-05,"ars":0.01460693,"aud":1.732e-05,"bch":3.3837e-08,"bdt":0.00142975,"bhd":4.3e-06,"bmd":1.162e-05,"bnb":1.3077e-08,"brl":6.288e-05,"btc":9.6444e-11,"cad":1.525e-05,"chf":8.73e-06,"clp":0.00964705,"cny":8.311e-05,"czk":0.00022613,"dkk":6.876e-05,"dot":2.37e-06,"eos":2.671e-05,"eth":2.739e-09,"eur":9.21e-06,"gbp":8.0e-06,"gel":3.149e-05,"hkd":9.159e-05,"huf":0.00366037,"idr":0.190991,"ils":3.783e-05,"inr":0.00102291,"jpy":0.00153525,"krw":0.0148347,"kwd":3.5e-06,"lkr":0.00347208,"ltc":1.0298e-07,"mmk":0.02438179,"mxn":0.00020875,"myr":4.767e-05,"ngn":0.01775269,"nok":0.00011515,"nzd":1.939e-05,"php":0.00065813,"pkr":0.00336987,"pln":3.862e-05,"rub":0.00084387,"sar":4.365e-05,"sek":9.841e-05,"sgd":1.416e-05,"sol":-1.0244805107e-08,"thb":0.00035077,"try":0.00047078,"twd":0.00033401,"uah":0.00049427,"usd":1.162e-05,"vef":1.16e-06,"vnd":0.304205,"xag":2.17184e-07,"xau":2.735e-09,"xdr":8.23e-06,"xlm":1.63e-05,"xrp":1.93e-06,"yfi":1.86e-09,"zar":0.00018899,"bits":9.644e-05,"link":4.87462e-07,"sats":0.00964438},"price_change_percentage_1h_in_currency":{"aed":1.13554,"ars":1.13817,"aud":1.17586,"bch":0.60065,"bdt":1.13554,"bhd":1.13903,"bmd":1.13554,"bnb":0.8634,"brl":1.11557,"btc":0.83899,"cad":1.13828,"chf":1.1268,"clp":1.32022,"cny":1.13554,"czk":1.15428,"dkk":1.13323,"dot":0.40855,"eos":0.07207,"eth":0.80995,"eur":1.14974,"gbp":1.1511,"gel":1.13554,"hkd":1.13297,"huf":1.12955,"idr":1.13554,"ils":1.13554,"inr":1.13602,"jpy":1.21486,"krw":1.13697,"kwd":1.16039,"lkr":1.13554,"ltc":0.49517,"mmk":1.13554,"mxn":1.19883,"myr":1.13554,"ngn":1.13554,"nok":1.11898,"nzd":1.15455,"php":1.13554,"pkr":1.13554,"pln":1.13022,"rub":1.15346,"sar":1.15024,"sek":1.16714,"sgd":1.14344,"sol":0.33309,"thb":1.16458,"try":1.17335,"twd":1.0894,"uah":1.13554,"usd":1.13554,"vef":1.13554,"vnd":1.13554,"xag":1.06739,"xau":1.05651,"xdr":1.13554,"xlm":0.72005,"xrp":0.38908,"yfi":0.26381,"zar":1.12492,"bits":0.83899,"link":0.39902,"sats":0.83899},"price_change_percentage_24h_in_currency":{"aed":7.89582,"ars":7.76725,"aud":7.64455,"bch":12.52048,"bdt":7.98979,"bhd":7.71486,"bmd":7.88113,"bnb":6.702,"brl":7.64143,"btc":7.68139,"cad":7.53597,"chf":7.3817,"clp":6.78725,"cny":7.85182,"czk":7.23872,"dkk":7.26232,"dot":7.20411,"eos":11.28059,"eth":6.94084,"eur":7.25801,"gbp":7.2754,"gel":7.88113,"hkd":7.91535,"huf":7.22922,"idr":7.93233,"ils":7.64075,"inr":8.05269,"jpy":7.00696,"krw":7.23132,"kwd":7.76394,"lkr":7.80742,"ltc":8.10502,"mmk":7.88113,"mxn":7.55579,"myr":7.61435,"ngn":7.86368,"nok":7.67273,"nzd":7.84085,"php":7.81501,"pkr":8.02068,"pln":7.16858,"rub":7.27706,"sar":7.89157,"sek":6.90334,"sgd":7.47094,"sol":-1.25071,"thb":7.34372,"try":7.90209,"twd":7.70176,"uah":8.02918,"usd":7.88113,"vef":7.88113,"vnd":7.88721,"xag":5.61697,"xau":6.20903,"xdr":7.94892,"xlm":5.10307,"xrp":4.52392,"yfi":7.75959,"zar":7.23106,"bits":7.68139,"link":6.37326,"sats":7.68139},"price_change_percentage_7d_in_currency":{"aed":24.80653,"ars":24.31577,"aud":25.31952,"bch":20.52915,"bdt":25.29458,"bhd":24.83831,"bmd":24.80653,"bnb":12.92614,"brl":24.34874,"btc":27.46604,"cad":24.63156,"chf":24.81576,"clp":22.95597,"cny":24.94582,"czk":24.26278,"dkk":24.51687,"dot":9.89012,"eos":13.6334,"eth":-0.26419,"eur":24.48757,"gbp":24.27563,"gel":24.80653,"hkd":24.80494,"huf":24.21129,"idr":25.32745,"ils":24.50678,"inr":25.26253,"jpy":24.53486,"krw":24.84005,"kwd":24.68115,"lkr":25.01433,"ltc":2.87284,"mmk":24.80653,"mxn":24.47253,"myr":24.30759,"ngn":25.05672,"nok":24.98461,"nzd":24.96899,"php":25.73619,"pkr":25.09452,"pln":24.13031,"rub":24.96717,"sar":24.83421,"sek":24.33302,"sgd":24.64639,"sol":3.19859,"thb":23.92219,"try":25.40266,"twd":24.75596,"uah":24.7573,"usd":24.80653,"vef":24.80653,"vnd":24.98556,"xag":22.14745,"xau":22.69547,"xdr":26.02819,"xlm":19.6874,"xrp":3.01633,"yfi":13.21404,"zar":22.76394,"bits":27.46604,"link":0.43328,"sats":27.46604},"price_change_percentage_14d_in_currency":{"aed":23.28306,"ars":24.45404,"aud":22.74734,"bch":16.30472,"bdt":22.43465,"bhd":23.29864,"bmd":23.28359,"bnb":6.52825,"brl":25.16041,"btc":13.3512,"cad":23.30765,"chf":23.22985,"clp":24.68498,"cny":23.30249,"czk":23.36912,"dkk":23.52099,"dot":-8.04628,"eos":-0.13093,"eth":-16.91078,"eur":23.44498,"gbp":24.35039,"gel":23.28359,"hkd":23.28988,"huf":23.22941,"idr":23.32285,"ils":23.55394,"inr":23.84077,"jpy":24.42884,"krw":23.92979,"kwd":23.27713,"lkr":23.47434,"ltc":-8.42597,"mmk":23.28359,"mxn":23.3528,"myr":23.31271,"ngn":23.19606,"nok":23.57525,"nzd":23.94187,"php":24.25236,"pkr":23.75195,"pln":23.32161,"rub":22.50803,"sar":23.31909,"sek":23.94974,"sgd":23.37031,"sol":-6.83161,"thb":21.76507,"try":24.58463,"twd":24.37092,"uah":23.16352,"usd":23.28359,"vef":23.28359,"vnd":23.33196,"xag":16.39522,"xau":20.97588,"xdr":14.75257,"xlm":-35.24513,"xrp":-21.28794,"yfi":1.9536,"zar":21.67741,"bits":13.3512,"link":-15.71576,"sats":13.3512},"price_change_percentage_30d_in_currency":{"aed":20.64258,"ars":32.10854,"aud":19.64978,"bch":6.96071,"bdt":19.74068,"bhd":20.62919,"bmd":20.61992,"bnb":-1.29682,"brl":21.83598,"btc":4.18885,"cad":20.19145,"chf":17.66711,"clp":22.28088,"cny":20.5544,"czk":17.93515,"dkk":18.94455,"dot":-12.1793,"eos":-7.25672,"eth":-26.75822,"eur":18.873,"gbp":20.32549,"gel":20.17646,"hkd":20.61246,"huf":17.81509,"idr":20.02803,"ils":15.81367,"inr":20.17372,"jpy":21.67376,"krw":21.46815,"kwd":20.2328,"lkr":20.90288,"ltc":-17.17125,"mmk":20.61992,"mxn":17.50605,"myr":20.13772,"ngn":19.11129,"nok":21.24814,"nzd":20.74663,"php":20.35118,"pkr":21.20841,"pln":18.2064,"rub":20.28297,"sar":20.5932,"sek":19.56899,"sgd":20.09467,"sol":-18.24123,"thb":18.61224,"try":22.85913,"twd":19.69737,"uah":20.86387,"usd":20.61992,"vef":20.61992,"vnd":20.76188,"xag":11.5364,"xau":19.4582,"xdr":19.41138,"xlm":-40.26865,"xrp":-31.03395,"yfi":-8.46121,"zar":18.05764,"bits":4.18885,"link":-26.8461,"sats":4.18885},"price_change_percentage_60d_in_currency":{"aed":12.37192,"ars":26.00485,"aud":10.46998,"bch":-5.67769,"bdt":12.1993,"bhd":12.36646,"bmd":12.37183,"bnb":0.2388,"brl":9.42036,"btc":5.90351,"cad":10.92629,"chf":8.19562,"clp":13.64918,"cny":11.93041,"czk":7.22708,"dkk":8.48427,"dot":22.43243,"eos":40.3846,"eth":-21.44484,"eur":8.41897,"gbp":11.81588,"gel":11.14148,"hkd":12.69917,"huf":7.32913,"idr":12.18664,"ils":4.70103,"inr":12.77041,"jpy":14.94516,"krw":12.41315,"kwd":11.75978,"lkr":13.26256,"ltc":-3.40041,"mmk":12.37183,"mxn":8.65809,"myr":11.35959,"ngn":8.19809,"nok":11.83753,"nzd":11.04808,"php":15.12102,"pkr":13.81512,"pln":8.2682,"rub":10.29472,"sar":12.39127,"sek":11.70588,"sgd":11.28126,"sol":1.78203,"thb":10.25096,"try":16.35696,"twd":9.75812,"uah":13.30033,"usd":12.37183,"vef":12.37183,"vnd":13.15272,"xag":-4.65768,"xau":8.8734,"xdr":9.56582,"xlm":-28.50094,"xrp":-23.99294,"yfi":7.00185,"zar":9.87123,"bits":5.90351,"link":-4.71711,"sats":5.90351},"price_change_percentage_200d_in_currency":{"aed":-98.94618,"ars":-98.69878,"aud":-98.99754,"bch":-99.07478,"bdt":-98.94651,"bhd":-98.94585,"bmd":-98.94618,"bnb":-99.02825,"brl":-99.04627,"btc":-99.13061,"cad":-98.99886,"chf":-99.0783,"clp":-98.99719,"cny":-98.96404,"czk":-99.09436,"dkk":-99.07409,"dot":-98.32548,"eos":-98.57256,"eth":-99.03602,"eur":-99.07483,"gbp":-99.03275,"gel":-98.98549,"hkd":-98.93629,"huf":-99.10726,"idr":-98.93889,"ils":-99.03396,"inr":-98.94033,"jpy":-99.01389,"krw":-99.00845,"kwd":-98.95701,"lkr":-98.91688,"ltc":-99.04319,"mmk":-98.94618,"mxn":-99.04463,"myr":-99.00336,"ngn":-98.95665,"nok":-99.06029,"nzd":-99.01183,"php":-98.96301,"pkr":-98.92116,"pln":-99.0812,"rub":-99.25756,"sar":-98.94731,"sek":-99.09475,"sgd":-99.01521,"sol":-98.89281,"thb":-99.01212,"try":-98.79545,"twd":-99.05981,"uah":-98.9541,"usd":-98.94618,"vef":-98.94618,"vnd":-98.91722,"xag":-99.20032,"xau":-99.17643,"xdr":-99.03506,"xlm":-99.04549,"xrp":-99.29693,"yfi":-98.57249,"zar":-99.00985,"bits":-99.13061,"link":-98.81498,"sats":-99.13061},"price_change_percentage_1y_in_currency":{},"market_cap_change_24h_in_currency":{"aed":42124,"ars":14452383,"aud":17094.88,"bch":32.940731,"bdt":1408673,"bhd":4231.12,"bmd":11448.61,"bnb":12.645445,"brl":61836,"btc":0.09543593,"cad":15084.97,"chf":8611.48,"clp":9488968,"cny":81869,"czk":222997,"dkk":67827,"dot":2311,"eos":24695,"eth":2.624826,"eur":9081.92,"gbp":7902.3,"gel":31026,"hkd":90200,"huf":3616907,"idr":188161964,"ils":37255,"inr":1007906,"jpy":1507812,"krw":14601554,"kwd":3447.26,"lkr":3420136,"ltc":101.036,"mmk":24019192,"mxn":205855,"myr":46950,"ngn":17488310,"nok":113472,"nzd":19028.66,"php":648293,"pkr":3320310,"pln":38096,"rub":833634,"sar":43011,"sek":96459,"sgd":13953.46,"sol":-12.70697943106859,"thb":346534,"try":463741,"twd":329148,"uah":487002,"usd":11448.61,"vef":1146.35,"vnd":299683133,"xag":213.58,"xau":2.69,"xdr":8104.17,"xlm":16023,"xrp":1739,"yfi":1.837658,"zar":185839,"bits":95436,"link":456.308,"sats":9543593},"market_cap_change_percentage_24h_in_currency":{"aed":7.81549,"ars":7.72424,"aud":7.58155,"bch":12.2058,"bdt":7.9094,"bhd":7.63467,"bmd":7.80082,"bnb":6.50173,"brl":7.54968,"btc":7.62591,"cad":7.48998,"chf":7.32206,"clp":6.70775,"cny":7.77153,"czk":7.17365,"dkk":7.19942,"dot":7.02575,"eos":10.33684,"eth":6.6594,"eur":7.19597,"gbp":7.2243,"gel":7.80082,"hkd":7.83207,"huf":7.17899,"idr":7.85198,"ils":7.56062,"inr":7.97225,"jpy":6.9134,"krw":7.15149,"kwd":7.68513,"lkr":7.72716,"ltc":7.98201,"mmk":7.80082,"mxn":7.48744,"myr":7.53423,"ngn":7.78338,"nok":7.59753,"nzd":7.73305,"php":7.73474,"pkr":7.94027,"pln":7.10511,"rub":7.22498,"sar":7.8128,"sek":6.79703,"sgd":7.39801,"sol":-1.55469,"thb":7.29149,"try":7.82093,"twd":7.62561,"uah":7.94876,"usd":7.80082,"vef":7.80082,"vnd":7.80689,"xag":5.55005,"xau":6.14428,"xdr":7.86856,"xlm":5.03668,"xrp":4.08095,"yfi":7.67835,"zar":7.14373,"bits":7.62591,"link":5.95677,"sats":7.62591},"total_supply":999912476.689,"max_supply":999998837.39,"max_supply_infinite":false,"circulating_supply":999912476.689,"last_updated":"2025-07-21T22:38:39.651Z"},"community_data":{"facebook_likes":null,"reddit_average_posts_48h":0.0,"reddit_average_comments_48h":0.0,"reddit_subscribers":0,"reddit_accounts_active_48h":0,"telegram_channel_user_count":623},"developer_data":{"forks":0,"stars":0,"subscribers":0,"total_issues":0,"closed_issues":0,"pull_requests_merged":0,"pull_request_contributors":0,"code_additions_deletions_4_weeks":{"additions":null,"deletions":null},"commit_count_4_weeks":0,"last_4_weeks_commit_activity_series":[]},"status_updates":[],"last_updated":"2025-07-21T22:38:39.651Z","tickers":[{"base":"3DKVGANSMTCXFKGGDAM299FAVXGNCW2411VXZTMRPUMP","target":"SO11111111111111111111111111111111111111112","market":{"name":"Raydium","identifier":"raydium2","has_trading_incentive":false},"last":8.072991321e-07,"volume":8663312.726921,"converted_last":{"btc":1.352e-09,"eth":4.2197e-08,"usd":0.00015907},"converted_volume":{"btc":0.01187197,"eth":0.37056689,"usd":1396.9},"trust_score":"yellow","bid_ask_spread_percentage":0.607193,"timestamp":"2025-07-21T21:07:48+00:00","last_traded_at":"2025-07-21T21:07:48+00:00","last_fetch_at":"2025-07-21T22:38:59+00:00","is_anomaly":false,"is_stale":false,"trade_url":"https://raydium.io/swap/?outputCurrency=3DkVGaNSMTcxFkgGDAm299FaVxgnCw2411vxZTmRpump","token_info_url":null,"coin_id":"omega-2","target_coin_id":"wrapped-solana"}]}