{"id":"txnscan","symbol":"txn","name":"TXNScan","web_slug":"txnscan","asset_platform_id":"ethereum","platforms":{"ethereum":"0x247e3866f743cce280433b865a669c9361421ecc"},"detail_platforms":{"ethereum":{"decimal_place":9,"contract_address":"0x247e3866f743cce280433b865a669c9361421ecc","geckoterminal_url":"https://www.geckoterminal.com/eth/tokens/0x247e3866f743cce280433b865a669c9361421ecc"}},"block_time_in_minutes":0,"hashing_algorithm":null,"categories":["Ethereum Ecosystem"],"preview_listing":false,"public_notice":null,"additional_notices":["Kindly be aware of \u003ca href='https://www.coingecko.com/en/glossary/rug-pulled' target='_blank'\u003eliquidity-related risks\u003c/a\u003e. This notice is not directed at any project in particular, and is more of a cautionary reminder.","The following token has a variable tax function on the smart contract to \u003ca href=\"https://support.coingecko.com/hc/en-us/articles/4499153900185-What-are-variable-taxes-on-Smart-Contracts-\"\u003echange tax rates post deployment\u003c/a\u003e. \u003cbr\u003e\nDo your own research and be careful if you are trading this token.\n"],"localization":{"en":"TXNScan","de":"","es":"","fr":"","it":"","pl":"","ro":"","hu":"","nl":"","pt":"","sv":"","vi":"","tr":"","ru":"","ja":"","zh":"","zh-tw":"","ko":"","ar":"","th":"","id":"","cs":"","da":"","el":"","hi":"","no":"","sk":"","uk":"","he":"","fi":"","bg":"","hr":"","lt":"","sl":""},"description":{"en":"As blockchain technology matures, the sheer volume and complexity of on-chain data continue to expand at breakneck speed. Traditional explorers, while indispensable tools for early adopters and developers, often present information in raw technical formats that are inaccessible to the average user. A typical blockchain transaction can be a labyrinth of hexadecimal input data, multiple token transfers, contract calls, and opaque technical indicators. This complexity discourages newcomers, forces professionals to waste time on manual interpretation, and restricts the blockchain’s full potential to a narrow, highly technical audience.\r\nTXNScan seeks to change this dynamic by placing advanced artificial intelligence (AI), intuitive interfaces, and intelligent narratives at the core of blockchain exploration. Rather than forcing users to decode complex contract interactions by themselves, TXNScan interprets data, offering clear human-readable explanations, contextual insights, and interactive visual representations. It transforms raw blockchain data into comprehensible stories and actionable intelligence, making the technology accessible to everyone—from curious newcomers to veteran developers and institutional analysts.","de":"","es":"","fr":"","it":"","pl":"","ro":"","hu":"","nl":"","pt":"","sv":"","vi":"","tr":"","ru":"","ja":"","zh":"","zh-tw":"","ko":"","ar":"","th":"","id":"","cs":"","da":"","el":"","hi":"","no":"","sk":"","uk":"","he":"","fi":"","bg":"","hr":"","lt":"","sl":""},"links":{"homepage":["https://txnscan.com/"],"whitepaper":"https://docs.txnscan.com/","blockchain_site":["https://etherscan.io/token/0x247e3866f743cce280433b865a669c9361421ecc","https://ethplorer.io/address/0x247E3866F743CcE280433b865A669c9361421ecc"],"official_forum_url":[],"chat_url":[],"announcement_url":[],"snapshot_url":null,"twitter_screen_name":"txnscan","facebook_username":null,"bitcointalk_thread_identifier":null,"telegram_channel_identifier":"txnscan","subreddit_url":null,"repos_url":{"github":[],"bitbucket":[]}},"image":{"thumb":"https://coin-images.coingecko.com/coins/images/53658/thumb/IMG_4607.jpeg?1737001129","small":"https://coin-images.coingecko.com/coins/images/53658/small/IMG_4607.jpeg?1737001129","large":"https://coin-images.coingecko.com/coins/images/53658/large/IMG_4607.jpeg?1737001129"},"country_origin":null,"genesis_date":null,"contract_address":"0x247e3866f743cce280433b865a669c9361421ecc","sentiment_votes_up_percentage":null,"sentiment_votes_down_percentage":null,"watchlist_portfolio_users":47,"market_cap_rank":10274,"market_data":{"current_price":{"aed":0.00033957,"ars":0.116072,"aud":0.00014102,"bch":1.76421e-07,"bdt":0.01121226,"bhd":3.485e-05,"bmd":9.245e-05,"bnb":1.15942e-07,"brl":0.00051458,"btc":7.73064e-10,"cad":0.00012575,"chf":7.34e-05,"clp":0.087895,"cny":0.00066289,"czk":0.00193969,"dkk":0.00058817,"dot":2.065e-05,"eos":0.00015397,"eth":2.4763e-08,"eur":7.879e-05,"gbp":6.839e-05,"gel":0.00025054,"hkd":0.00072573,"huf":0.03145091,"idr":1.51,"ils":0.0003097,"inr":0.00797917,"jpy":0.0135573,"krw":0.12753,"kwd":2.821e-05,"lkr":0.02778021,"ltc":7.64903e-07,"mmk":0.194052,"mxn":0.00172388,"myr":0.00039074,"ngn":0.141175,"nok":0.00093177,"nzd":0.00015407,"php":0.00526062,"pkr":0.02624589,"pln":0.00033501,"rub":0.00725786,"sar":0.00034684,"sek":0.00087987,"sgd":0.00011825,"sol":4.54587e-07,"thb":0.00297725,"try":0.00373865,"twd":0.00271747,"uah":0.00384746,"usd":9.245e-05,"vef":9.26e-06,"vnd":2.42,"xag":2.36e-06,"xau":2.7014e-08,"xdr":6.421e-05,"xlm":0.00019677,"xrp":2.626e-05,"yfi":1.5113e-08,"zar":0.00162339,"bits":0.00077306,"link":4.71e-06,"sats":0.077306},"total_value_locked":null,"mcap_to_tvl_ratio":null,"fdv_to_tvl_ratio":null,"roi":null,"ath":{"aed":0.04053016,"ars":11.6,"aud":0.01773336,"bch":3.212e-05,"bdt":1.35,"bhd":0.00415906,"bmd":0.01103486,"bnb":1.815e-05,"brl":0.064862,"btc":1.09145e-07,"cad":0.01597648,"chf":0.01005564,"clp":10.86,"cny":0.0793,"czk":0.267508,"dkk":0.079389,"dot":0.00216785,"eos":0.01710745,"eth":3.97e-06,"eur":0.01063859,"gbp":0.00889208,"gel":0.03171156,"hkd":0.085994,"huf":4.34,"idr":179.96,"ils":0.03945728,"inr":0.956161,"jpy":1.71,"krw":16.02,"kwd":0.00340387,"lkr":3.28,"ltc":0.00010469,"mmk":23.15,"mxn":0.228193,"myr":0.04913824,"ngn":18.15,"nok":0.125162,"nzd":0.01954291,"php":0.644851,"pkr":3.08,"pln":0.04481385,"rub":1.085,"sar":0.04138572,"sek":0.122062,"sgd":0.01496546,"sol":5.00375e-07,"thb":0.371621,"try":0.395719,"twd":0.363317,"uah":0.461208,"usd":0.01103486,"vef":0.00110492,"vnd":276.75,"xag":0.00035058,"xau":3.95e-06,"xdr":0.00843753,"xlm":0.03009874,"xrp":0.00407662,"yfi":1.75e-06,"zar":0.205832,"bits":0.109145,"link":0.00052437,"sats":10.91},"ath_change_percentage":{"aed":-99.16154,"ars":-98.99866,"aud":-99.20475,"bch":-99.45024,"bdt":-99.16643,"bhd":-99.16131,"bmd":-99.16156,"bnb":-99.36055,"brl":-99.20592,"btc":-99.29108,"cad":-99.21253,"chf":-99.26979,"clp":-99.19013,"cny":-99.16362,"czk":-99.2746,"dkk":-99.25882,"dot":-99.04776,"eos":-99.10036,"eth":-99.37627,"eur":-99.25907,"gbp":-99.23055,"gel":-99.20934,"hkd":-99.15543,"huf":-99.27473,"idr":-99.16331,"ils":-99.21449,"inr":-99.16488,"jpy":-99.205,"krw":-99.20389,"kwd":-99.17063,"lkr":-99.15352,"ltc":-99.26957,"mmk":-99.16116,"mxn":-99.2441,"myr":-99.2042,"ngn":-99.22139,"nok":-99.25541,"nzd":-99.21137,"php":-99.18377,"pkr":-99.14655,"pln":-99.25205,"rub":-99.33036,"sar":-99.16139,"sek":-99.27898,"sgd":-99.20964,"sol":-9.18302,"thb":-99.19858,"try":-99.05455,"twd":-99.25167,"uah":-99.16514,"usd":-99.16156,"vef":-99.16156,"vnd":-99.12622,"xag":-99.32646,"xau":-99.3153,"xdr":-99.23842,"xlm":-99.34547,"xrp":-99.35516,"yfi":-99.13493,"zar":-99.21098,"bits":-99.29108,"link":-99.10149,"sats":-99.29108},"ath_date":{"aed":"2025-01-31T09:19:26.343Z","ars":"2025-01-31T09:19:26.343Z","aud":"2025-01-31T09:19:26.343Z","bch":"2025-02-03T16:52:34.388Z","bdt":"2025-01-31T09:19:26.343Z","bhd":"2025-01-31T09:19:26.343Z","bmd":"2025-01-31T09:19:26.343Z","bnb":"2025-02-03T16:52:34.388Z","brl":"2025-01-31T09:19:26.343Z","btc":"2025-02-03T16:52:34.388Z","cad":"2025-01-31T09:19:26.343Z","chf":"2025-01-31T09:19:26.343Z","clp":"2025-01-31T09:19:26.343Z","cny":"2025-01-31T09:19:26.343Z","czk":"2025-01-31T09:19:26.343Z","dkk":"2025-01-31T09:19:26.343Z","dot":"2025-02-03T16:52:34.388Z","eos":"2025-02-03T16:52:34.388Z","eth":"2025-02-03T16:52:34.388Z","eur":"2025-01-31T09:19:26.343Z","gbp":"2025-01-31T09:19:26.343Z","gel":"2025-01-31T02:00:00.255Z","hkd":"2025-01-31T09:19:26.343Z","huf":"2025-01-31T09:19:26.343Z","idr":"2025-01-31T09:19:26.343Z","ils":"2025-01-31T09:19:26.343Z","inr":"2025-01-31T09:19:26.343Z","jpy":"2025-01-31T09:19:26.343Z","krw":"2025-01-31T02:00:00.255Z","kwd":"2025-01-31T09:19:26.343Z","lkr":"2025-01-31T09:19:26.343Z","ltc":"2025-02-03T16:52:34.388Z","mmk":"2025-01-31T09:19:26.343Z","mxn":"2025-01-31T09:19:26.343Z","myr":"2025-01-31T09:19:26.343Z","ngn":"2025-02-03T16:52:34.388Z","nok":"2025-01-31T09:19:26.343Z","nzd":"2025-01-31T02:00:00.255Z","php":"2025-01-31T09:19:26.343Z","pkr":"2025-01-31T09:19:26.343Z","pln":"2025-01-31T09:19:26.343Z","rub":"2025-01-31T02:00:00.255Z","sar":"2025-01-31T09:19:26.343Z","sek":"2025-01-31T09:19:26.343Z","sgd":"2025-01-31T09:19:26.343Z","sol":"2025-07-17T07:47:12.507Z","thb":"2025-01-31T09:19:26.343Z","try":"2025-01-31T09:19:26.343Z","twd":"2025-01-31T09:19:26.343Z","uah":"2025-01-31T09:19:26.343Z","usd":"2025-01-31T09:19:26.343Z","vef":"2025-01-31T09:19:26.343Z","vnd":"2025-01-31T09:19:26.343Z","xag":"2025-01-31T02:00:00.255Z","xau":"2025-01-31T09:19:26.343Z","xdr":"2025-01-31T09:19:26.343Z","xlm":"2025-02-03T16:52:34.388Z","xrp":"2025-02-03T16:52:34.388Z","yfi":"2025-02-03T16:52:34.388Z","zar":"2025-01-31T09:19:26.343Z","bits":"2025-02-03T16:52:34.388Z","link":"2025-02-03T16:52:34.388Z","sats":"2025-02-03T16:52:34.388Z"},"atl":{"aed":0.00023661,"ars":0.073672,"aud":9.843e-05,"bch":1.23648e-07,"bdt":0.0078765,"bhd":2.43e-05,"bmd":6.443e-05,"bnb":9.8975e-08,"brl":0.00035091,"btc":5.98403e-10,"cad":8.817e-05,"chf":5.125e-05,"clp":0.059985,"cny":0.00046211,"czk":0.00135596,"dkk":0.00041008,"dot":1.648e-05,"eos":0.0001019,"eth":2.4737e-08,"eur":5.497e-05,"gbp":4.711e-05,"gel":0.00017524,"hkd":0.00050575,"huf":0.02193223,"idr":1.046,"ils":0.00021722,"inr":0.00550917,"jpy":0.00928252,"krw":0.087746,"kwd":1.963e-05,"lkr":0.01931346,"ltc":7.43337e-07,"mmk":0.13517,"mxn":0.00120807,"myr":0.00027171,"ngn":0.099226,"nok":0.00064891,"nzd":0.00010612,"php":0.00364456,"pkr":0.0182766,"pln":0.00023314,"rub":0.00506465,"sar":0.00024164,"sek":0.00061136,"sgd":8.221e-05,"sol":4.11499e-07,"thb":0.00208687,"try":0.00257129,"twd":0.00187505,"uah":0.00268512,"usd":6.443e-05,"vef":6.45e-06,"vnd":1.68,"xag":1.76e-06,"xau":1.9125e-08,"xdr":4.496e-05,"xlm":0.00015,"xrp":2.585e-05,"yfi":1.2506e-08,"zar":0.00114159,"bits":0.0005984,"link":4.72e-06,"sats":0.05984},"atl_change_percentage":{"aed":43.62327,"ars":57.66866,"aud":43.27378,"bch":42.79101,"bdt":42.46022,"bhd":43.51997,"bmd":43.60372,"bnb":17.25755,"brl":46.77733,"btc":29.30151,"cad":42.69148,"chf":43.26907,"clp":46.63958,"cny":43.52564,"czk":43.10804,"dkk":43.48971,"dot":25.24196,"eos":51.03302,"eth":0.08576,"eur":43.39518,"gbp":45.23263,"gel":43.07576,"hkd":43.60427,"huf":43.46638,"idr":43.97152,"ils":42.68687,"inr":44.94188,"jpy":46.09563,"krw":45.38787,"kwd":43.81157,"lkr":43.94929,"ltc":2.87771,"mmk":43.67217,"mxn":42.78199,"myr":43.91584,"ngn":42.38655,"nok":43.61776,"nzd":45.23611,"php":44.41988,"pkr":43.71433,"pln":43.76694,"rub":43.40366,"sar":43.6311,"sek":43.95677,"sgd":43.87675,"sol":10.43172,"thb":42.71381,"try":45.50287,"twd":45.00014,"uah":43.39874,"usd":43.60372,"vef":43.60372,"vnd":43.83462,"xag":34.40479,"xau":41.35979,"xdr":42.93486,"xlm":31.3359,"xrp":1.69283,"yfi":21.03533,"zar":42.26189,"bits":29.30151,"link":-0.10941,"sats":29.30151},"atl_date":{"aed":"2025-06-29T16:48:14.929Z","ars":"2025-07-05T02:37:37.533Z","aud":"2025-07-01T07:25:14.235Z","bch":"2025-07-01T08:43:11.314Z","bdt":"2025-06-29T16:48:14.929Z","bhd":"2025-06-29T16:48:14.929Z","bmd":"2025-06-29T16:48:14.929Z","bnb":"2025-06-30T16:01:51.407Z","brl":"2025-07-04T16:25:15.572Z","btc":"2025-06-29T14:55:08.446Z","cad":"2025-07-01T07:25:14.235Z","chf":"2025-07-01T09:04:10.736Z","clp":"2025-06-29T16:48:14.929Z","cny":"2025-06-29T16:48:14.929Z","czk":"2025-07-04T16:25:15.572Z","dkk":"2025-06-29T16:48:14.929Z","dot":"2025-06-08T15:24:43.779Z","eos":"2025-05-30T14:14:59.412Z","eth":"2025-07-23T01:19:25.350Z","eur":"2025-06-29T16:48:14.929Z","gbp":"2025-07-01T07:25:14.235Z","gel":"2025-06-29T16:48:14.929Z","hkd":"2025-06-29T16:48:14.929Z","huf":"2025-07-01T07:25:14.235Z","idr":"2025-06-29T16:48:14.929Z","ils":"2025-07-04T16:25:15.572Z","inr":"2025-06-29T16:48:14.929Z","jpy":"2025-07-01T09:04:10.736Z","krw":"2025-07-01T07:25:14.235Z","kwd":"2025-06-29T16:48:14.929Z","lkr":"2025-06-29T16:48:14.929Z","ltc":"2025-06-29T17:28:19.831Z","mmk":"2025-06-29T16:48:14.929Z","mxn":"2025-07-04T16:25:15.572Z","myr":"2025-07-01T07:25:14.235Z","ngn":"2025-07-04T16:25:15.572Z","nok":"2025-06-18T13:32:39.626Z","nzd":"2025-07-01T09:04:10.736Z","php":"2025-06-29T16:48:14.929Z","pkr":"2025-06-29T16:48:14.929Z","pln":"2025-06-29T16:48:14.929Z","rub":"2025-06-29T16:48:14.929Z","sar":"2025-06-29T16:48:14.929Z","sek":"2025-06-29T16:48:14.929Z","sgd":"2025-06-29T16:48:14.929Z","sol":"2025-06-30T16:01:51.407Z","thb":"2025-06-29T16:48:14.929Z","try":"2025-06-29T16:48:14.929Z","twd":"2025-06-29T16:48:14.929Z","uah":"2025-06-29T16:48:14.929Z","usd":"2025-06-29T16:48:14.929Z","vef":"2025-06-29T16:48:14.929Z","vnd":"2025-06-29T16:48:14.929Z","xag":"2025-07-04T16:25:15.572Z","xau":"2025-06-13T02:57:43.742Z","xdr":"2025-06-29T16:48:14.929Z","xlm":"2025-07-14T01:34:48.121Z","xrp":"2025-07-14T15:04:17.318Z","yfi":"2025-06-30T14:01:55.604Z","zar":"2025-07-01T09:04:10.736Z","bits":"2025-06-29T14:55:08.446Z","link":"2025-07-23T01:41:02.444Z","sats":"2025-06-29T14:55:08.446Z"},"market_cap":{"aed":33983,"ars":11615786,"aud":14102.46,"bch":17.655858,"bdt":1122089,"bhd":3488.16,"bmd":9252.09,"bnb":11.605601,"brl":51505,"btc":0.07737443,"cad":12581.07,"chf":7342.74,"clp":8796243,"cny":66325,"czk":194049,"dkk":58842,"dot":2064,"eos":15391,"eth":2.475836,"eur":7882.42,"gbp":6842.01,"gel":25073,"hkd":72628,"huf":3146538,"idr":150566730,"ils":30994,"inr":798510,"jpy":1356136,"krw":12757181,"kwd":2823.08,"lkr":2780159,"ltc":76.473,"mmk":19420146,"mxn":172490,"myr":39104,"ngn":14128410,"nok":93194,"nzd":15412.07,"php":526347,"pkr":2626609,"pln":33518,"rub":726289,"sar":34707,"sek":88009,"sgd":11828.11,"sol":45.442526,"thb":297825,"try":374131,"twd":271882,"uah":385042,"usd":9252.09,"vef":926.41,"vnd":241821594,"xag":236.13,"xau":2.7,"xdr":6425.84,"xlm":19700,"xrp":2629,"yfi":1.513709,"zar":162405,"bits":77374,"link":471.147,"sats":7737443},"market_cap_rank":10274,"fully_diluted_valuation":{"aed":33983,"ars":11615786,"aud":14102.46,"bch":17.655858,"bdt":1122089,"bhd":3488.16,"bmd":9252.09,"bnb":11.605601,"brl":51505,"btc":0.07737443,"cad":12581.07,"chf":7342.74,"clp":8796243,"cny":66325,"czk":194049,"dkk":58842,"dot":2064,"eos":15391,"eth":2.475836,"eur":7882.42,"gbp":6842.01,"gel":25073,"hkd":72628,"huf":3146538,"idr":150566730,"ils":30994,"inr":798510,"jpy":1356136,"krw":12757181,"kwd":2823.08,"lkr":2780159,"ltc":76.473,"mmk":19420146,"mxn":172490,"myr":39104,"ngn":14128410,"nok":93194,"nzd":15412.07,"php":526347,"pkr":2626609,"pln":33518,"rub":726289,"sar":34707,"sek":88009,"sgd":11828.11,"sol":45.442526,"thb":297825,"try":374131,"twd":271882,"uah":385042,"usd":9252.09,"vef":926.41,"vnd":241821594,"xag":236.13,"xau":2.7,"xdr":6425.84,"xlm":19700,"xrp":2629,"yfi":1.513709,"zar":162405,"bits":77374,"link":471.147,"sats":7737443},"market_cap_fdv_ratio":1.0,"total_volume":{"aed":29.07,"ars":9935.95,"aud":12.07,"bch":0.01510195,"bdt":959.79,"bhd":2.98,"bmd":7.91,"bnb":0.00992484,"brl":44.05,"btc":6.618e-05,"cad":10.76,"chf":6.28,"clp":7523.95,"cny":56.74,"czk":166.04,"dkk":50.35,"dot":1.767814,"eos":13.17979,"eth":0.00211976,"eur":6.74,"gbp":5.85,"gel":21.45,"hkd":62.12,"huf":2692.25,"idr":128846,"ils":26.51,"inr":683.03,"jpy":1160.53,"krw":10916.76,"kwd":2.41,"lkr":2378.04,"ltc":0.06547708,"mmk":16611.21,"mxn":147.57,"myr":33.45,"ngn":12084.87,"nok":79.76,"nzd":13.19,"php":450.32,"pkr":2246.7,"pln":28.68,"rub":621.29,"sar":29.69,"sek":75.32,"sgd":10.12,"sol":0.03891348,"thb":254.86,"try":320.04,"twd":232.62,"uah":329.35,"usd":7.91,"vef":0.792416,"vnd":206844,"xag":0.202154,"xau":0.00231243,"xdr":5.5,"xlm":16.843786,"xrp":2.247509,"yfi":0.00129374,"zar":138.97,"bits":66.18,"link":0.40284279,"sats":6617.57},"high_24h":{"aed":0.00034011,"ars":0.116255,"aud":0.00014119,"bch":1.76754e-07,"bdt":0.01127043,"bhd":3.491e-05,"bmd":9.26e-05,"bnb":1.16084e-07,"brl":0.00051549,"btc":7.74528e-10,"cad":0.00012592,"chf":7.349e-05,"clp":0.088036,"cny":0.00066418,"czk":0.00194212,"dkk":0.00058891,"dot":2.069e-05,"eos":0.0001549,"eth":2.4797e-08,"eur":7.889e-05,"gbp":6.848e-05,"gel":0.00025094,"hkd":0.00072688,"huf":0.03149172,"idr":1.51,"ils":0.0003102,"inr":0.00799291,"jpy":0.01357271,"krw":0.127679,"kwd":2.825e-05,"lkr":0.02792437,"ltc":7.81925e-07,"mmk":0.194364,"mxn":0.00172635,"myr":0.00039137,"ngn":0.141707,"nok":0.00093272,"nzd":0.00015425,"php":0.00526788,"pkr":0.02637862,"pln":0.00033546,"rub":0.00726897,"sar":0.00034736,"sek":0.00088083,"sgd":0.00011838,"sol":4.54682e-07,"thb":0.00298074,"try":0.00374444,"twd":0.0027211,"uah":0.00386709,"usd":9.26e-05,"vef":9.27e-06,"vnd":2.42,"xag":2.36e-06,"xau":2.7057e-08,"xdr":6.46e-05,"xlm":0.00019764,"xrp":2.631e-05,"yfi":1.5162e-08,"zar":0.00162541,"bits":0.00077453,"link":4.74e-06,"sats":0.077453},"low_24h":{"aed":0.00033817,"ars":0.115595,"aud":0.0001404,"bch":1.76407e-07,"bdt":0.0111662,"bhd":3.47e-05,"bmd":9.207e-05,"bnb":1.15392e-07,"brl":0.00051232,"btc":7.70373e-10,"cad":0.0001252,"chf":7.307e-05,"clp":0.087534,"cny":0.00066058,"czk":0.00193089,"dkk":0.0005855,"dot":2.061e-05,"eos":0.00015332,"eth":2.4737e-08,"eur":7.843e-05,"gbp":6.808e-05,"gel":0.00024951,"hkd":0.00072273,"huf":0.0313098,"idr":1.5,"ils":0.00030843,"inr":0.00794828,"jpy":0.01350368,"krw":0.12709,"kwd":2.809e-05,"lkr":0.0276661,"ltc":7.63516e-07,"mmk":0.193255,"mxn":0.00171673,"myr":0.000389,"ngn":0.140669,"nok":0.00092746,"nzd":0.00015333,"php":0.00523984,"pkr":0.02613809,"pln":0.00033354,"rub":0.00722738,"sar":0.00034538,"sek":0.00087557,"sgd":0.00011772,"sol":4.52044e-07,"thb":0.00296387,"try":0.0037231,"twd":0.00270888,"uah":0.00383166,"usd":9.207e-05,"vef":9.22e-06,"vnd":2.41,"xag":2.35e-06,"xau":2.6876e-08,"xdr":6.395e-05,"xlm":0.0001966,"xrp":2.623e-05,"yfi":1.5124e-08,"zar":0.00161643,"bits":0.00077037,"link":4.71e-06,"sats":0.077037},"price_change_24h":-1.21315002821e-07,"price_change_percentage_24h":-0.13105,"price_change_percentage_7d":20.67356,"price_change_percentage_14d":40.24244,"price_change_percentage_30d":39.89353,"price_change_percentage_60d":-16.57741,"price_change_percentage_200d":0.0,"price_change_percentage_1y":0.0,"market_cap_change_24h":-5.015223342422,"market_cap_change_percentage_24h":-0.05418,"price_change_24h_in_currency":{"aed":-4.45590005362e-07,"ars":-0.000150335891863973,"aud":-1.63022834157e-07,"bch":-3.33314628e-10,"bdt":-5.8176808293489e-05,"bhd":-4.647596087e-08,"bmd":-1.21315002821e-07,"bnb":4.64347e-10,"brl":-6.01182430573e-07,"btc":-7.83457e-13,"cad":-1.3112570203e-07,"chf":-5.1784556678e-08,"clp":-0.000115337812632163,"cny":-1.286434887333e-06,"czk":-1.246171466938e-06,"dkk":-4.58920603125e-07,"dot":4.4951e-08,"eos":-9.2994869932e-07,"eth":3.389e-12,"eur":-5.5257260455e-08,"gbp":-6.2063530997e-08,"gel":-3.28763657645e-07,"hkd":-9.43244739192e-07,"huf":-2.039564170412e-05,"idr":0.00014474,"ils":-4.06399193701e-07,"inr":-1.3733703036667e-05,"jpy":1.264e-05,"krw":-0.000148425486971582,"kwd":-3.6368242578e-08,"lkr":-0.000144160379602805,"ltc":-1.4255483391e-08,"mmk":-0.000254640190921585,"mxn":-1.903308955271e-06,"myr":-2.81310124643e-07,"ngn":-0.000531469966289222,"nok":-4.74354615473e-07,"nzd":-1.19877448124e-07,"php":-3.43143333436e-06,"pkr":-0.000132732621204286,"pln":-2.74548606898e-07,"rub":-8.936777284106e-06,"sar":-4.28011496638e-07,"sek":-1.50565798354e-07,"sgd":-8.2315110025e-08,"sol":2.408e-09,"thb":-2.50270141325e-07,"try":-4.831805004864e-06,"twd":-3.25109890253e-06,"uah":-1.9633036823838e-05,"usd":-1.21315002821e-07,"vef":-1.2147271232e-08,"vnd":-0.004090463362732777,"xag":3.269e-09,"xau":3.9534e-11,"xdr":-3.92518409007e-07,"xlm":-8.11024228462e-07,"xrp":-8.047063756e-09,"yfi":-3.3438628e-11,"zar":-1.602598485275e-06,"bits":-7.83457124966e-07,"link":-1.8271122339e-08,"sats":-7.8345712496625e-05},"price_change_percentage_1h_in_currency":{"aed":-0.13105,"ars":-0.12935,"aud":-0.11547,"bch":-0.18858,"bdt":-0.51619,"bhd":-0.13317,"bmd":-0.13105,"bnb":0.40211,"brl":-0.11669,"btc":-0.10124,"cad":-0.10417,"chf":-0.07051,"clp":-0.13105,"cny":-0.19369,"czk":-0.0642,"dkk":-0.07796,"dot":0.21814,"eos":-0.60037,"eth":0.01369,"eur":-0.07008,"gbp":-0.09067,"gel":-0.13105,"hkd":-0.1298,"huf":-0.06481,"idr":0.00962,"ils":-0.13105,"inr":-0.17182,"jpy":0.09334,"krw":-0.11625,"kwd":-0.12876,"lkr":-0.51625,"ltc":-1.8296,"mmk":-0.13105,"mxn":-0.11029,"myr":-0.07194,"ngn":-0.37505,"nok":-0.05088,"nzd":-0.07775,"php":-0.06519,"pkr":-0.50318,"pln":-0.08189,"rub":-0.12298,"sar":-0.12325,"sek":-0.01711,"sgd":-0.06956,"sol":0.5326,"thb":-0.00841,"try":-0.12907,"twd":-0.11949,"uah":-0.50769,"usd":-0.13105,"vef":-0.13105,"vnd":-0.169,"xag":0.13862,"xau":0.14656,"xdr":-0.6076,"xlm":-0.41048,"xrp":-0.03064,"yfi":-0.22076,"zar":-0.09862,"bits":-0.10124,"link":-0.38675,"sats":-0.10124},"price_change_percentage_24h_in_currency":{"aed":-0.13105,"ars":-0.12935,"aud":-0.11547,"bch":-0.18858,"bdt":-0.51619,"bhd":-0.13317,"bmd":-0.13105,"bnb":0.40211,"brl":-0.11669,"btc":-0.10124,"cad":-0.10417,"chf":-0.07051,"clp":-0.13105,"cny":-0.19369,"czk":-0.0642,"dkk":-0.07796,"dot":0.21814,"eos":-0.60037,"eth":0.01369,"eur":-0.07008,"gbp":-0.09067,"gel":-0.13105,"hkd":-0.1298,"huf":-0.06481,"idr":0.00962,"ils":-0.13105,"inr":-0.17182,"jpy":0.09334,"krw":-0.11625,"kwd":-0.12876,"lkr":-0.51625,"ltc":-1.8296,"mmk":-0.13105,"mxn":-0.11029,"myr":-0.07194,"ngn":-0.37505,"nok":-0.05088,"nzd":-0.07775,"php":-0.06519,"pkr":-0.50318,"pln":-0.08189,"rub":-0.12298,"sar":-0.12325,"sek":-0.01711,"sgd":-0.06956,"sol":0.5326,"thb":-0.00841,"try":-0.12907,"twd":-0.11949,"uah":-0.50769,"usd":-0.13105,"vef":-0.13105,"vnd":-0.169,"xag":0.13862,"xau":0.14656,"xdr":-0.6076,"xlm":-0.41048,"xrp":-0.03064,"yfi":-0.22076,"zar":-0.09862,"bits":-0.10124,"link":-0.38675,"sats":-0.10124},"price_change_percentage_7d_in_currency":{"aed":20.67356,"ars":18.44208,"aud":20.53213,"bch":16.05254,"bdt":20.94923,"bhd":20.66652,"bmd":20.67356,"bnb":4.53839,"brl":20.14257,"btc":21.08809,"cad":19.77902,"chf":20.13832,"clp":18.16982,"cny":20.71229,"czk":19.73385,"dkk":20.0122,"dot":6.7525,"eos":9.88368,"eth":-2.79607,"eur":19.97129,"gbp":19.89721,"gel":20.67356,"hkd":20.6751,"huf":19.71436,"idr":20.77,"ils":20.38141,"inr":21.15539,"jpy":19.79296,"krw":20.4114,"kwd":20.45525,"lkr":20.51763,"ltc":-5.02201,"mmk":20.73108,"mxn":20.15483,"myr":19.93576,"ngn":20.41725,"nok":19.76824,"nzd":20.1678,"php":21.20501,"pkr":20.35845,"pln":19.74063,"rub":21.30044,"sar":20.71082,"sek":19.41142,"sgd":20.38696,"sol":-3.48538,"thb":19.57451,"try":21.37499,"twd":20.75737,"uah":20.08681,"usd":20.67356,"vef":20.67356,"vnd":20.75191,"xag":17.51988,"xau":17.87002,"xdr":20.51999,"xlm":15.0134,"xrp":0.47788,"yfi":10.34194,"zar":18.32679,"bits":21.08809,"link":-2.72617,"sats":21.08809},"price_change_percentage_14d_in_currency":{"aed":40.24148,"ars":56.72086,"aud":40.2076,"bch":29.08961,"bdt":38.69514,"bhd":40.41078,"bmd":40.24244,"bnb":14.74645,"brl":43.97237,"btc":26.69092,"cad":40.12921,"chf":40.14746,"clp":43.37003,"cny":40.3403,"czk":40.62471,"dkk":40.85438,"dot":4.36895,"eos":10.69428,"eth":-6.08604,"eur":40.78541,"gbp":41.66726,"gel":39.72684,"hkd":40.24958,"huf":40.78229,"idr":40.93107,"ils":40.28285,"inr":41.07023,"jpy":42.35149,"krw":41.98271,"kwd":40.1671,"lkr":40.50185,"ltc":0.14243,"mmk":40.30928,"mxn":40.36377,"myr":40.42518,"ngn":39.97753,"nok":40.13558,"nzd":41.65524,"php":41.20401,"pkr":40.29531,"pln":41.04426,"rub":40.06443,"sar":40.2927,"sek":39.60151,"sgd":40.86524,"sol":1.18831,"thb":39.81579,"try":42.35846,"twd":42.50652,"uah":39.98835,"usd":40.24244,"vef":40.24244,"vnd":40.06804,"xag":32.31033,"xau":36.73743,"xdr":29.108,"xlm":-29.45149,"xrp":-11.90168,"yfi":15.31745,"zar":39.80208,"bits":26.69092,"link":-6.60558,"sats":26.69092},"price_change_percentage_30d_in_currency":{"aed":39.91753,"ars":53.76678,"aud":39.01782,"bch":22.81383,"bdt":38.79311,"bhd":39.79786,"bmd":39.89353,"bnb":12.48267,"brl":41.37692,"btc":22.26201,"cad":39.12851,"chf":35.81163,"clp":41.01186,"cny":39.52188,"czk":35.9973,"dkk":37.24959,"dot":12.61208,"eos":17.29146,"eth":-6.27347,"eur":37.15014,"gbp":39.26531,"gel":39.37922,"hkd":39.89585,"huf":35.78423,"idr":39.33598,"ils":35.05565,"inr":39.67426,"jpy":41.81362,"krw":40.54785,"kwd":39.38601,"lkr":39.97923,"ltc":-2.19155,"mmk":39.96021,"mxn":37.18586,"myr":39.26746,"ngn":38.30225,"nok":41.47856,"nzd":40.78648,"php":39.3938,"pkr":40.19898,"pln":36.31679,"rub":39.89819,"sar":39.86926,"sek":38.27703,"sgd":39.32081,"sol":-0.40803,"thb":38.10948,"try":43.15198,"twd":39.2139,"uah":39.69582,"usd":39.89353,"vef":39.89353,"vnd":40.08357,"xag":31.93648,"xau":38.64092,"xdr":36.97487,"xlm":-25.93584,"xrp":-14.94961,"yfi":13.75608,"zar":36.57848,"bits":22.26201,"link":-8.82428,"sats":22.26201},"price_change_percentage_60d_in_currency":{"aed":-16.57741,"ars":-7.82056,"aud":-18.35984,"bch":-30.28955,"bdt":-16.84041,"bhd":-16.59289,"bmd":-16.57741,"bnb":-28.77437,"brl":-17.18298,"btc":-22.06297,"cad":-18.15096,"chf":-20.15165,"clp":-15.88376,"cny":-16.97111,"czk":-20.70797,"dkk":-19.80214,"dot":-7.7122,"eos":6.19895,"eth":-40.5171,"eur":-19.84654,"gbp":-17.17207,"gel":-17.49079,"hkd":-16.33499,"huf":-20.70912,"idr":-16.9914,"ils":-22.28005,"inr":-16.25907,"jpy":-15.16787,"krw":-16.77181,"kwd":-17.09447,"lkr":-16.16439,"ltc":-31.47663,"mmk":-16.53764,"mxn":-19.40761,"myr":-17.52384,"ngn":-19.8671,"nok":-17.55209,"nzd":-17.9336,"php":-14.86963,"pkr":-15.92059,"pln":-19.86979,"rub":-17.79954,"sar":-16.56328,"sek":-17.62713,"sgd":-17.44711,"sol":-26.44048,"thb":-18.24654,"try":-13.31424,"twd":-18.42977,"uah":-16.26405,"usd":-16.57741,"vef":-16.57741,"vnd":-16.06501,"xag":-29.44069,"xau":-19.68342,"xdr":-19.55151,"xlm":-46.26136,"xrp":-42.41957,"yfi":-19.14393,"zar":-18.63549,"bits":-22.06297,"link":-28.80763,"sats":-22.06297},"price_change_percentage_200d_in_currency":{},"price_change_percentage_1y_in_currency":{},"market_cap_change_24h_in_currency":{"aed":-18.42091533671919,"ars":-6416.420399300754,"aud":-16.19799818104002,"bch":-0.019563958427571748,"bdt":-4954.62287531211,"bhd":-1.81674752286699,"bmd":-5.01522334242145,"bnb":0.05784265,"brl":-12.182160859869327,"btc":-1.0310270292024e-05,"cad":-6.6068273068194685,"chf":-1.9714389633554674,"clp":-4768.123288342729,"cny":-93.3462082779879,"czk":-44.55297102101031,"dkk":-21.13916663548298,"dot":3.64755,"eos":-99.02912181327156,"eth":-0.000124679953378948,"eur":-2.402838597007758,"gbp":-3.1348620164772,"gel":-13.59125525797208,"hkd":-39.43352564415545,"huf":-592.5488272598013,"idr":62794,"ils":-16.800747435961966,"inr":-780.6976284506964,"jpy":1670.58,"krw":-10615.131144419312,"kwd":-1.4284618799479176,"lkr":-12277.669859648682,"ltc":-1.4430818516735542,"mmk":-10526.953795749694,"mxn":-87.53916620108066,"myr":1.95,"ngn":-42280.085928158835,"nok":-30.577452826604713,"nzd":-6.7991295595311385,"php":-58.46809775312431,"pkr":-11252.997331701685,"pln":-9.560014314985892,"rub":-390.5661093451781,"sar":-20.386889626955963,"sek":6.63,"sgd":-4.958220727130538,"sol":0.22463978,"thb":74.62,"try":-217.58620611520018,"twd":-189.94154713657917,"uah":-1667.147214612225,"usd":-5.01522334242145,"vef":-0.5021743132772372,"vnd":-223048.50721800327,"xag":0.300884,"xau":0.00603281,"xdr":-34.309387310288,"xlm":-57.538669975550874,"xrp":2.43158,"yfi":-0.000975324850372106,"zar":-94.41186826719786,"bits":-10.310270292000496,"link":-1.2811321907277033,"sats":-1031.027029203251},"market_cap_change_percentage_24h_in_currency":{"aed":-0.05418,"ars":-0.05521,"aud":-0.11473,"bch":-0.11068,"bdt":-0.43961,"bhd":-0.05206,"bmd":-0.05418,"bnb":0.5009,"brl":-0.02365,"btc":-0.01332,"cad":-0.05249,"chf":-0.02684,"clp":-0.05418,"cny":-0.14054,"czk":-0.02295,"dkk":-0.03591,"dot":0.17701,"eos":-0.63933,"eth":-0.00504,"eur":-0.03047,"gbp":-0.0458,"gel":-0.05418,"hkd":-0.05427,"huf":-0.01883,"idr":0.04172,"ils":-0.05418,"inr":-0.09767,"jpy":0.12334,"krw":-0.08314,"kwd":-0.05057,"lkr":-0.43968,"ltc":-1.8521,"mmk":-0.05418,"mxn":-0.05072,"myr":0.00498,"ngn":-0.29836,"nok":-0.0328,"nzd":-0.0441,"php":-0.01111,"pkr":-0.4266,"pln":-0.02851,"rub":-0.05375,"sar":-0.05871,"sek":0.00754,"sgd":-0.0419,"sol":0.49679,"thb":0.02506,"try":-0.05812,"twd":-0.06981,"uah":-0.43111,"usd":-0.05418,"vef":-0.05418,"vnd":-0.09215,"xag":0.12759,"xau":0.22365,"xdr":-0.53109,"xlm":-0.29122,"xrp":0.09258,"yfi":-0.06439,"zar":-0.0581,"bits":-0.01332,"link":-0.27118,"sats":-0.01332},"total_supply":100000000.0,"max_supply":100000000.0,"max_supply_infinite":false,"circulating_supply":100000000.0,"last_updated":"2025-07-23T01:53:03.226Z"},"community_data":{"facebook_likes":null,"reddit_average_posts_48h":0.0,"reddit_average_comments_48h":0.0,"reddit_subscribers":0,"reddit_accounts_active_48h":0,"telegram_channel_user_count":290},"developer_data":{"forks":0,"stars":0,"subscribers":0,"total_issues":0,"closed_issues":0,"pull_requests_merged":0,"pull_request_contributors":0,"code_additions_deletions_4_weeks":{"additions":null,"deletions":null},"commit_count_4_weeks":0,"last_4_weeks_commit_activity_series":[]},"status_updates":[],"last_updated":"2025-07-23T01:53:03.226Z","tickers":[{"base":"0X247E3866F743CCE280433B865A669C9361421ECC","target":"0XC02AAA39B223FE8D0A0E5C4F27EAD9083C756CC2","market":{"name":"Uniswap V2 (Ethereum)","identifier":"uniswap_v2","has_trading_incentive":false},"last":2.474584084e-08,"volume":85601.809125,"converted_last":{"btc":7.73036e-10,"eth":2.4746e-08,"usd":9.245e-05},"converted_volume":{"btc":6.617e-05,"eth":0.00211832,"usd":7.91},"trust_score":"yellow","bid_ask_spread_percentage":0.629007,"timestamp":"2025-07-23T00:48:57+00:00","last_traded_at":"2025-07-23T00:48:57+00:00","last_fetch_at":"2025-07-23T01:51:45+00:00","is_anomaly":false,"is_stale":false,"trade_url":"https://app.uniswap.org/explore/tokens/ethereum/0x247e3866f743cce280433b865a669c9361421ecc","token_info_url":"https://v2.info.uniswap.org/token/0x247e3866f743cce280433b865a669c9361421ecc","coin_id":"txnscan","target_coin_id":"weth"}]}